.gitignore
.gitmodules
LICENSE.txt
MANIFEST.in
README.rst
setup.py
doc/Makefile
doc/postprocess.py
doc/rtd-pip-requirements.txt
doc/source/chemistry.rst
doc/source/conf.py
doc/source/contribute.rst
doc/source/examples.rst
doc/source/getting_started.rst
doc/source/index.rst
doc/source/physics.rst
doc/source/release.rst
doc/source/scripts.analyze_txtlog.rst
doc/source/scripts.change_ext.rst
doc/source/scripts.mkbkupcp.rst
doc/source/scripts.rst
doc/source/scripts.tachyon_render.rst
doc/source/scripts.tga2png.rst
doc/source/scripts.timestamp_frames.rst
doc/source/scripts.txtlog2xlsx.rst
doc/source/tools.datautils.rst
doc/source/tools.mpltools.rst
doc/source/tools.refdata.rst
doc/source/tools.rst
doc/source/_static/Nanotube_Logo_200x200.png
doc/source/_static/default.css
doc/source/_static/logo.png
doc/source/_templates/indexsidebar.html
doc/source/_templates/layout.html
doc/source/_templates/autosummary/class.rst
doc/source/tutorial/index.rst
doc/source/tutorial/intro.rst
doc/source/tutorial/plotting_data.rst
doc/source/tutorial/scripts.rst
doc/source/tutorial/tools.rst
doc/sphinxext/ipython_console_highlighting.py
doc/sphinxext/numpydoc/.git
doc/sphinxext/numpydoc/.gitignore
doc/sphinxext/numpydoc/LICENSE.txt
doc/sphinxext/numpydoc/MANIFEST.in
doc/sphinxext/numpydoc/README.txt
doc/sphinxext/numpydoc/setup.py
doc/sphinxext/numpydoc/numpydoc/__init__.py
doc/sphinxext/numpydoc/numpydoc/comment_eater.py
doc/sphinxext/numpydoc/numpydoc/compiler_unparse.py
doc/sphinxext/numpydoc/numpydoc/docscrape.py
doc/sphinxext/numpydoc/numpydoc/docscrape_sphinx.py
doc/sphinxext/numpydoc/numpydoc/linkcode.py
doc/sphinxext/numpydoc/numpydoc/numpydoc.py
doc/sphinxext/numpydoc/numpydoc/phantom_import.py
doc/sphinxext/numpydoc/numpydoc/plot_directive.py
doc/sphinxext/numpydoc/numpydoc/traitsdoc.py
doc/sphinxext/numpydoc/numpydoc/tests/test_docscrape.py
doc/sphinxext/numpydoc/numpydoc/tests/test_linkcode.py
doc/sphinxext/numpydoc/numpydoc/tests/test_phantom_import.py
pykit_sci.egg-info/PKG-INFO
pykit_sci.egg-info/SOURCES.txt
pykit_sci.egg-info/dependency_links.txt
pykit_sci.egg-info/entry_points.txt
pykit_sci.egg-info/not-zip-safe
pykit_sci.egg-info/requires.txt
pykit_sci.egg-info/top_level.txt