Metadata-Version: 1.1
Name: pykit-sci
Version: 0.2.1
Summary: pykit-sci: collection of python modules for science.
Home-page: http://github.com/androomerrill/pykit-sci
Author: Andrew Merrill
Author-email: androomerrill@gmail.com
License: BSD 2-Clause
Platform: Linux
Platform: Mac OS-X
Platform: Unix
Platform: Windows
Classifier: Development Status :: 4 - Beta
Classifier: Intended Audience :: Science/Research
Classifier: License :: OSI Approved :: BSD License
Classifier: Operating System :: MacOS :: MacOS X
Classifier: Operating System :: Microsoft :: Windows
Classifier: Operating System :: POSIX
Classifier: Operating System :: Unix
Classifier: Programming Language :: Python
Classifier: Programming Language :: Python :: 2.7
Classifier: Programming Language :: Python :: 3.4
Classifier: Topic :: Software Development
Classifier: Topic :: Scientific/Engineering
